LICENSE
MANIFEST.in
README.rst
setup.py
chomsky/__init__.py
chomsky/buffer.py
chomsky/exceptions.py
chomsky/grammar.py
chomsky/matchers.py
chomsky/result_list.py
chomsky/util.py
chomsky.egg-info/PKG-INFO
chomsky.egg-info/SOURCES.txt
chomsky.egg-info/dependency_links.txt
chomsky.egg-info/top_level.txt