Metadata-Version: 1.2
Name: chomsky
Version: 2.0.0
Summary: Another language grammar parser.  Inspired by modgrammar and pyparsing
Home-page: https://github.com/colinta/chomsky
Author: Colin T.A. Gray
Author-email: colinta@gmail.com
License: BSD
Keywords: chomsky language grammar parser
Platform: any
Classifier: Programming Language :: Python
Classifier: Programming Language :: Python :: 3
Classifier: Development Status :: 4 - Beta
Classifier: Environment :: Console
Classifier: License :: OSI Approved :: BSD License
Classifier: Operating System :: OS Independent
Classifier: Intended Audience :: End Users/Desktop
Classifier: Intended Audience :: Developers
Classifier: Topic :: Text Processing
Classifier: Topic :: Text Processing :: General
Classifier: Topic :: Internet
Requires-Python: >3.0.0
